# 变量作用域

```python
b = 6
def foo(a):
    print(a)
    print(b) # 这里会抛出错误
    b = 9
```

因为 Python 编译函数主体时，判断 `b` 是局部变量，但尝试获取 `b` 的值时，发现 `b` 还没有绑定值

如果想让 Python 认为是全局变量，并且需要在函数内修改，就要使用 `global`

```python
b = 6
def foo(a):
    global b
    print(a)
    print(b)
    b = 9
```

模块全局作用域
函数局部作用域
非局部作用域

第一个函数的字节码为

```
0 LOAD_GLOBAL              0 (print)
2 LOAD_FAST                0 (a)
4 CALL_FUNCTION            1
6 POP_TOP

8 LOAD_GLOBAL              0 (print)
10 LOAD_FAST                1 (b)
12 CALL_FUNCTION            1
14 POP_TOP

16 LOAD_CONST               1 (9)
18 STORE_FAST               1 (b)
20 LOAD_CONST               0 (None)
22 RETURN_VALUE
```

可以看到这里加载 `b` 的字节码是 `10 LOAD_FAST`

第二个函数的字节码为

```
0 LOAD_GLOBAL              0 (print)
2 LOAD_FAST                0 (a)
4 CALL_FUNCTION            1
6 POP_TOP

8 LOAD_GLOBAL              0 (print)
10 LOAD_GLOBAL              1 (b)
12 CALL_FUNCTION            1
14 POP_TOP

16 LOAD_CONST               1 (9)
18 STORE_GLOBAL             1 (b)
20 LOAD_CONST               0 (None)
22 RETURN_VALUE
```

这里加载 `b` 的字节码是 `10 LOAD_GLOBAL`

